{
  "branding": {
    "companyName": "PowerWood AG",
    "companyNameAr": "دليل تجميع باور وود",
    "logo": "/logos/pw-logo-1770394451050.png",
    "primaryColor": "#0ea5e9",
    "secondaryColor": "#1b1c50",
    "favicon": "/favicons/png-favicon-1770395632477.png"
  },
  "terminology": {
    "itemSingular": {
      "en": "Assembly",
      "ar": "تجميع"
    },
    "itemPlural": {
      "en": "Assemblies",
      "ar": "تجميعات"
    },
    "urlSlug": "assembly"
  },
  "features": {
    "enableQRCodes": true,
    "enableAudio": true,
    "enableAnnotations": true,
    "enableDarkMode": true
  },
  "contact": {
    "email": "support@powerwood.com",
    "website": "https://powerwood.com"
  }
}